ancli/__init__.py
ancli/__main__.py
ancli/ancli.py
ancli/version.py
ancli-0.1.3.dist-info/LICENSE
ancli-0.1.3.dist-info/METADATA
ancli-0.1.3.dist-info/WHEEL
ancli-0.1.3.dist-info/top_level.txt
ancli-0.1.3.dist-info/RECORD
