Metadata-Version: 2.1
Name: ancli
Version: 0.1.3
Summary: Small utility to convert functions into CLI
Home-page: https://github.com/devforfu/ancli
Maintainer: devforfu
License: UNKNOWN
Download-URL: https://github.com/devforfu/ancli/archive/v0.1.3.tar.gz
Platform: UNKNOWN
